{"results":[{"type":"4","wkid":"1","sourceResults":"sourceFinal","sourceString":"","statusDate":"2017-09-25 00:54:50","counted":"1","countedTotal":"1","percentCounted":"","percentTurnout":"76.2","percentTurnoutPre":"71.7","percentTurnoutDiff":"4.5","absoluteVoters":"","absolute1":"171905","absolute2":"171905","absoluteEntitled":"225659","winnerName":"Petra Nicolaisen","winnerparty_id":"p200","winnerId":"311","results":[{"id":"p200","partyname":"CDU","percent1":"40.0","percent2":"34.2","absolute1":"68102","absolute2":"58307","seats":"","percent2Pre":"38.2","percent2Diff":"-4"},{"id":"p100","partyname":"SPD","percent1":"28.0","percent2":"23.7","absolute1":"47697","absolute2":"40376","seats":"","percent2Pre":"32.6","percent2Diff":"-8.9"},{"id":"p300","partyname":"Gr\u00fcne","percent1":"10.5","percent2":"13.1","absolute1":"17899","absolute2":"22290","seats":"","percent2Pre":"9.8","percent2Diff":"3.3"},{"id":"p400","partyname":"FDP","percent1":"6.5","percent2":"11.1","absolute1":"11143","absolute2":"18948","seats":"","percent2Pre":"5.0","percent2Diff":"6.1"},{"id":"p500","partyname":"Linke","percent1":"7.1","percent2":"8.2","absolute1":"12138","absolute2":"13995","seats":"","percent2Pre":"5.7","percent2Diff":"2.5"},{"id":"p644","partyname":"AfD","percent1":"6.2","percent2":"6.8","absolute1":"10581","absolute2":"11647","seats":"","percent2Pre":"4.1","percent2Diff":"2.7"},{"id":"p735","partyname":"Die Partei","percent1":"0","percent2":"1.2","absolute1":"0","absolute2":"2091","seats":"","percent2Pre":"","percent2Diff":""},{"id":"p608","partyname":"Freie W\u00e4hler","percent1":"1.1","percent2":"0.7","absolute1":"1943","absolute2":"1189","seats":"","percent2Pre":"0.6","percent2Diff":"0.1"},{"id":"p661","partyname":"BGE","percent1":"0","percent2":"0.5","absolute1":"0","absolute2":"843","seats":"","percent2Pre":"","percent2Diff":""},{"id":"p910","partyname":"NPD","percent1":"0","percent2":"0.2","absolute1":"0","absolute2":"354","seats":"","percent2Pre":"0.6","percent2Diff":"-0.4"},{"id":"p611","partyname":"\u00d6DP","percent1":"0","percent2":"0.2","absolute1":"0","absolute2":"297","seats":"","percent2Pre":"","percent2Diff":""},{"id":"p637","partyname":"MLPD","percent1":"0","percent2":"0.0","absolute1":"0","absolute2":"59","seats":"","percent2Pre":"0.0","percent2Diff":"0"}]}]}