{"results":[{"type":"4","wkid":"160","sourceResults":"sourceFinal","sourceString":"","statusDate":"2017-09-25 01:12:10","counted":"1","countedTotal":"1","percentCounted":"","percentTurnout":"79.3","percentTurnoutPre":"73.6","percentTurnoutDiff":"5.7","absoluteVoters":"","absolute1":"186818","absolute2":"186818","absoluteEntitled":"235455","winnerName":"Arnold Vaatz","winnerparty_id":"p200","winnerId":"161","results":[{"id":"p644","partyname":"AfD","percent1":"22.3","percent2":"23.3","absolute1":"41197","absolute2":"43119","seats":"","percent2Pre":"7.0","percent2Diff":"16.3"},{"id":"p200","partyname":"CDU","percent1":"25.6","percent2":"23.1","absolute1":"47183","absolute2":"42791","seats":"","percent2Pre":"38.6","percent2Diff":"-15.5"},{"id":"p500","partyname":"Linke","percent1":"17.5","percent2":"17.3","absolute1":"32395","absolute2":"32035","seats":"","percent2Pre":"18.1","percent2Diff":"-0.8"},{"id":"p100","partyname":"SPD","percent1":"11.1","percent2":"9.7","absolute1":"20589","absolute2":"17973","seats":"","percent2Pre":"14.0","percent2Diff":"-4.3"},{"id":"p400","partyname":"FDP","percent1":"7.0","percent2":"9.6","absolute1":"12842","absolute2":"17683","seats":"","percent2Pre":"3.2","percent2Diff":"6.4"},{"id":"p300","partyname":"Gr\u00fcne","percent1":"8.6","percent2":"9.0","absolute1":"15832","absolute2":"16587","seats":"","percent2Pre":"9.5","percent2Diff":"-0.5"},{"id":"p735","partyname":"Die Partei","percent1":"2.7","percent2":"2.1","absolute1":"4994","absolute2":"3847","seats":"","percent2Pre":"","percent2Diff":""},{"id":"p601","partyname":"Tierschutzpartei","percent1":"0","percent2":"1.4","absolute1":"0","absolute2":"2530","seats":"","percent2Pre":"","percent2Diff":""},{"id":"p608","partyname":"Freie W\u00e4hler","percent1":"1.5","percent2":"1.0","absolute1":"2768","absolute2":"1927","seats":"","percent2Pre":"1.9","percent2Diff":"-0.9"},{"id":"p609","partyname":"Piraten","percent1":"1.5","percent2":"0.8","absolute1":"2696","absolute2":"1500","seats":"","percent2Pre":"4.4","percent2Diff":"-3.6"},{"id":"p910","partyname":"NPD","percent1":"0.6","percent2":"0.7","absolute1":"1160","absolute2":"1371","seats":"","percent2Pre":"2.7","percent2Diff":"-2"},{"id":"p611","partyname":"\u00d6DP","percent1":"1.2","percent2":"0.6","absolute1":"2141","absolute2":"1100","seats":"","percent2Pre":"","percent2Diff":""},{"id":"p661","partyname":"BGE","percent1":"0","percent2":"0.6","absolute1":"0","absolute2":"1040","seats":"","percent2Pre":"","percent2Diff":""},{"id":"p787","partyname":"DiB","percent1":"0","percent2":"0.4","absolute1":"0","absolute2":"757","seats":"","percent2Pre":"","percent2Diff":""},{"id":"p670","partyname":"V-Partei","percent1":"0","percent2":"0.2","absolute1":"0","absolute2":"403","seats":"","percent2Pre":"","percent2Diff":""},{"id":"p637","partyname":"MLPD","percent1":"0.2","percent2":"0.1","absolute1":"372","absolute2":"255","seats":"","percent2Pre":"0.2","percent2Diff":"-0.1"},{"id":"p602","partyname":"B\u00fcSo","percent1":"0.3","percent2":"0.1","absolute1":"499","absolute2":"218","seats":"","percent2Pre":"0.2","percent2Diff":"-0.1"}]}]}