{"results":[{"type":"4","wkid":"33","sourceResults":"sourceFinal","sourceString":"","statusDate":"2017-09-24 22:03:28","counted":"1","countedTotal":"1","percentCounted":"","percentTurnout":"76.5","percentTurnoutPre":"73.7","percentTurnoutDiff":"2.7","absoluteVoters":"","absolute1":"148297","absolute2":"148297","absoluteEntitled":"193959","winnerName":"Axel Knoerig","winnerparty_id":"p200","winnerId":"280","results":[{"id":"p200","partyname":"CDU","percent1":"44.6","percent2":"37.9","absolute1":"65462","absolute2":"55829","seats":"","percent2Pre":"43.5","percent2Diff":"-5.6"},{"id":"p100","partyname":"SPD","percent1":"27.3","percent2":"25.5","absolute1":"40101","absolute2":"37505","seats":"","percent2Pre":"31.5","percent2Diff":"-6"},{"id":"p400","partyname":"FDP","percent1":"7.0","percent2":"10.5","absolute1":"10284","absolute2":"15514","seats":"","percent2Pre":"4.9","percent2Diff":"5.6"},{"id":"p644","partyname":"AfD","percent1":"8.1","percent2":"8.4","absolute1":"11956","absolute2":"12433","seats":"","percent2Pre":"3.4","percent2Diff":"5"},{"id":"p300","partyname":"Gr\u00fcne","percent1":"7.7","percent2":"8.1","absolute1":"11252","absolute2":"11990","seats":"","percent2Pre":"8.2","percent2Diff":"-0.1"},{"id":"p500","partyname":"Linke","percent1":"5.3","percent2":"6.1","absolute1":"7758","absolute2":"8951","seats":"","percent2Pre":"4.5","percent2Diff":"1.6"},{"id":"p601","partyname":"Tierschutzpartei","percent1":"0","percent2":"0.9","absolute1":"0","absolute2":"1353","seats":"","percent2Pre":"0.8","percent2Diff":"0.1"},{"id":"p735","partyname":"Die Partei","percent1":"0","percent2":"0.7","absolute1":"0","absolute2":"1095","seats":"","percent2Pre":"","percent2Diff":""},{"id":"p608","partyname":"Freie W\u00e4hler","percent1":"0","percent2":"0.5","absolute1":"0","absolute2":"668","seats":"","percent2Pre":"0.5","percent2Diff":"0"},{"id":"p609","partyname":"Piraten","percent1":"0","percent2":"0.3","absolute1":"0","absolute2":"476","seats":"","percent2Pre":"1.5","percent2Diff":"-1.2"},{"id":"p910","partyname":"NPD","percent1":"0","percent2":"0.2","absolute1":"0","absolute2":"366","seats":"","percent2Pre":"0.8","percent2Diff":"-0.6"},{"id":"p661","partyname":"BGE","percent1":"0","percent2":"0.2","absolute1":"0","absolute2":"258","seats":"","percent2Pre":"","percent2Diff":""},{"id":"p611","partyname":"\u00d6DP","percent1":"0","percent2":"0.2","absolute1":"0","absolute2":"223","seats":"","percent2Pre":"","percent2Diff":""},{"id":"p786","partyname":"DM","percent1":"0","percent2":"0.1","absolute1":"0","absolute2":"205","seats":"","percent2Pre":"","percent2Diff":""},{"id":"p670","partyname":"V-Partei","percent1":"0","percent2":"0.1","absolute1":"0","absolute2":"190","seats":"","percent2Pre":"","percent2Diff":""},{"id":"p787","partyname":"DiB","percent1":"0","percent2":"0.1","absolute1":"0","absolute2":"167","seats":"","percent2Pre":"","percent2Diff":""},{"id":"p637","partyname":"MLPD","percent1":"0","percent2":"0.0","absolute1":"0","absolute2":"31","seats":"","percent2Pre":"0.0","percent2Diff":"0"},{"id":"p616","partyname":"DKP","percent1":"0","percent2":"0.0","absolute1":"0","absolute2":"19","seats":"","percent2Pre":"","percent2Diff":""}]}]}